odoo/addons/delivery_deliverea/README.rst
odoo/addons/delivery_deliverea/__init__.py
odoo/addons/delivery_deliverea/__manifest__.py
odoo/addons/delivery_deliverea/controllers/__init__.py
odoo/addons/delivery_deliverea/controllers/main.py
odoo/addons/delivery_deliverea/data/deliverea_states_data.xml
odoo/addons/delivery_deliverea/data/ir_cron.xml
odoo/addons/delivery_deliverea/data/product_packaging_data.xml
odoo/addons/delivery_deliverea/i18n/delivery_deliverea.pot
odoo/addons/delivery_deliverea/i18n/es.po
odoo/addons/delivery_deliverea/i18n/it.po
odoo/addons/delivery_deliverea/models/__init__.py
odoo/addons/delivery_deliverea/models/carrier_deliverea_parameter.py
odoo/addons/delivery_deliverea/models/carrier_deliverea_service.py
odoo/addons/delivery_deliverea/models/deliverea_distribution_center.py
odoo/addons/delivery_deliverea/models/deliverea_request.py
odoo/addons/delivery_deliverea/models/deliverea_state.py
odoo/addons/delivery_deliverea/models/delivery_carrier.py
odoo/addons/delivery_deliverea/models/stock_package_type.py
odoo/addons/delivery_deliverea/models/stock_picking.py
odoo/addons/delivery_deliverea/readme/CONFIGURE.rst
odoo/addons/delivery_deliverea/readme/CONTRIBUTORS.rst
odoo/addons/delivery_deliverea/readme/CREDITS.rst
odoo/addons/delivery_deliverea/readme/DESCRIPTION.rst
odoo/addons/delivery_deliverea/readme/HISTORY.rst
odoo/addons/delivery_deliverea/readme/INSTALL.rst
odoo/addons/delivery_deliverea/readme/USAGE.rst
odoo/addons/delivery_deliverea/security/ir.model.access.csv
odoo/addons/delivery_deliverea/static/description/icon.png
odoo/addons/delivery_deliverea/static/description/index.html
odoo/addons/delivery_deliverea/tests/__init__.py
odoo/addons/delivery_deliverea/tests/carrier_labels_data.py
odoo/addons/delivery_deliverea/tests/carrier_services_data.py
odoo/addons/delivery_deliverea/tests/test_delivery_deliverea.py
odoo/addons/delivery_deliverea/tests/test_webhook.py
odoo/addons/delivery_deliverea/tests/tools.py
odoo_addon_delivery_deliverea-16.0.1.1.0.3.dist-info/METADATA
odoo_addon_delivery_deliverea-16.0.1.1.0.3.dist-info/WHEEL
odoo_addon_delivery_deliverea-16.0.1.1.0.3.dist-info/top_level.txt
odoo_addon_delivery_deliverea-16.0.1.1.0.3.dist-info/RECORD
